ccg/__init__.py
ccg/__main__.py
ccg/cache.py
ccg/cli.py
ccg/config.py
ccg/core.py
ccg/git.py
ccg/git_strategies.py
ccg/logging.py
ccg/platform_utils.py
ccg/progress.py
ccg/utils.py
conventional_commits_generator-2.3.0.dist-info/METADATA
conventional_commits_generator-2.3.0.dist-info/WHEEL
conventional_commits_generator-2.3.0.dist-info/entry_points.txt
conventional_commits_generator-2.3.0.dist-info/licenses/LICENSE
conventional_commits_generator-2.3.0.dist-info/RECORD
