Metadata-Version: 2.4
Name: conventional-commits-generator
Version: 2.3.0
Summary: Interactive CLI tool for creating standardized commit messages following conventional commits
Project-URL: Homepage, https://github.com/EgydioBNeto/conventional-commits-generator
Project-URL: Repository, https://github.com/EgydioBNeto/conventional-commits-generator
Project-URL: Issues, https://github.com/EgydioBNeto/conventional-commits-generator/issues
Project-URL: Changelog, https://github.com/EgydioBNeto/conventional-commits-generator/releases
Author-email: Egydio Bolonhezi <egydiobolonhezi@gmail.com>
License: MIT License
License-File: LICENSE
Keywords: cli,commit,conventional-commits,developer-tools,git
Classifier: Development Status :: 5 - Production/Stable
Classifier: Environment :: Console
Classifier: Intended Audience :: Developers
Classifier: License :: OSI Approved :: MIT License
Classifier: Natural Language :: English
Classifier: Operating System :: OS Independent
Classifier: Programming Language :: Python :: 3
Classifier: Programming Language :: Python :: 3.9
Classifier: Programming Language :: Python :: 3.10
Classifier: Programming Language :: Python :: 3.11
Classifier: Programming Language :: Python :: 3.12
Classifier: Programming Language :: Python :: 3.13
Classifier: Topic :: Software Development :: Version Control :: Git
Classifier: Topic :: Utilities
Requires-Python: >=3.9
Requires-Dist: prompt-toolkit>=3.0.52
Provides-Extra: dev
Requires-Dist: pre-commit>=4.3.0; extra == 'dev'
Requires-Dist: tox>=4.31.0; extra == 'dev'
Provides-Extra: docs
Requires-Dist: mkdocs-git-revision-date-localized-plugin>=1.4.7; extra == 'docs'
Requires-Dist: mkdocs-material>=9.6.22; extra == 'docs'
Requires-Dist: mkdocs-minify-plugin>=0.8.0; extra == 'docs'
Requires-Dist: mkdocs>=1.6.1; extra == 'docs'
Requires-Dist: pymdown-extensions>=10.16.1; extra == 'docs'
Provides-Extra: quality
Requires-Dist: bandit[toml]>=1.8.6; extra == 'quality'
Requires-Dist: pylint>=3.0.0; extra == 'quality'
Requires-Dist: radon>=6.0.1; extra == 'quality'
Requires-Dist: vulture>=2.14; extra == 'quality'
Provides-Extra: test
Requires-Dist: hypothesis>=6.142.2; extra == 'test'
Requires-Dist: pytest-cov>=7.0.0; extra == 'test'
Requires-Dist: pytest-mock>=3.15.1; extra == 'test'
Requires-Dist: pytest>=8.4.2; extra == 'test'
